movement/__init__.py
movement/cli_entrypoint.py
movement/filtering.py
movement/sample_data.py
movement/transforms.py
movement/io/__init__.py
movement/io/load_bboxes.py
movement/io/load_poses.py
movement/io/nwb.py
movement/io/save_bboxes.py
movement/io/save_poses.py
movement/kinematics/__init__.py
movement/kinematics/distances.py
movement/kinematics/kinematics.py
movement/kinematics/kinetic_energy.py
movement/kinematics/orientation.py
movement/napari/__init__.py
movement/napari/convert.py
movement/napari/layer_styles.py
movement/napari/loader_widgets.py
movement/napari/meta_widget.py
movement/napari/napari.yaml
movement/plots/__init__.py
movement/plots/occupancy.py
movement/plots/trajectory.py
movement/roi/__init__.py
movement/roi/base.py
movement/roi/conditions.py
movement/roi/line.py
movement/roi/polygon.py
movement/utils/__init__.py
movement/utils/broadcasting.py
movement/utils/logging.py
movement/utils/reports.py
movement/utils/vector.py
movement/validators/__init__.py
movement/validators/arrays.py
movement/validators/datasets.py
movement/validators/files.py
movement-0.13.0.dist-info/licenses/LICENSE
movement-0.13.0.dist-info/METADATA
movement-0.13.0.dist-info/WHEEL
movement-0.13.0.dist-info/entry_points.txt
movement-0.13.0.dist-info/top_level.txt
movement-0.13.0.dist-info/RECORD
