Metadata-Version: 2.4
Name: movement
Version: 0.13.0
Summary: A Python toolbox for analysing animal body movements across space and time
Author-email: Nikoloz Sirmpilatze <niko.sirbiladze@gmail.com>, Chang Huan Lo <changhuan.lo@ucl.ac.uk>, Sofía Miñano <s.minano@ucl.ac.uk>
License: BSD-3-Clause
Project-URL: Homepage, https://github.com/neuroinformatics-unit/movement
Project-URL: Bug Tracker, https://github.com/neuroinformatics-unit/movement/issues
Project-URL: Documentation, https://movement.neuroinformatics.dev/
Project-URL: Source Code, https://github.com/neuroinformatics-unit/movement
Project-URL: User Support, https://neuroinformatics.zulipchat.com/#narrow/stream/406001-Movement
Classifier: Development Status :: 3 - Alpha
Classifier: Programming Language :: Python
Classifier: Programming Language :: Python :: 3
Classifier: Programming Language :: Python :: 3.11
Classifier: Programming Language :: Python :: 3.12
Classifier: Programming Language :: Python :: 3.13
Classifier: Operating System :: OS Independent
Classifier: License :: OSI Approved :: BSD License
Classifier: Framework :: napari
Requires-Python: >=3.11.0
License-File: LICENSE
Requires-Dist: numpy>=2.0.0
Requires-Dist: pandas
Requires-Dist: scipy<1.17.0
Requires-Dist: h5py
Requires-Dist: netCDF4<1.7.3
Requires-Dist: tables>=3.10.1
Requires-Dist: attrs
Requires-Dist: pooch
Requires-Dist: tqdm
Requires-Dist: shapely
Requires-Dist: sleap-io
Requires-Dist: xarray[accel,io,viz]
Requires-Dist: PyYAML
Requires-Dist: napari-video>=0.2.13
Requires-Dist: pyvideoreader>=0.5.3
Requires-Dist: qt-niu
Requires-Dist: loguru
Requires-Dist: pynwb
Requires-Dist: ndx-pose>=0.2.1
Provides-Extra: napari
Requires-Dist: napari[all]>=0.6.0; extra == "napari"
Provides-Extra: dev
Requires-Dist: pytest; extra == "dev"
Requires-Dist: pytest-cov; extra == "dev"
Requires-Dist: pytest-mock; extra == "dev"
Requires-Dist: coverage; extra == "dev"
Requires-Dist: tox; extra == "dev"
Requires-Dist: mypy; extra == "dev"
Requires-Dist: pre-commit; extra == "dev"
Requires-Dist: ruff; extra == "dev"
Requires-Dist: codespell; extra == "dev"
Requires-Dist: setuptools_scm; extra == "dev"
Requires-Dist: pandas-stubs; extra == "dev"
Requires-Dist: types-attrs; extra == "dev"
Requires-Dist: check-manifest; extra == "dev"
Requires-Dist: types-PyYAML; extra == "dev"
Requires-Dist: types-requests; extra == "dev"
Requires-Dist: pytest-qt; extra == "dev"
Requires-Dist: scipy-stubs; extra == "dev"
Requires-Dist: types-shapely; extra == "dev"
Requires-Dist: movement[napari]; extra == "dev"
Dynamic: license-file
